{
 "espireDate": "N",
 "format": "text",
 "jSonReasons": [
  "kw_cracked",
  "re_url",
  "lg_en"
 ],
 "key": "CqJ8dy9C",
 "pasteDate": "Feb 12, 2018, 11:14:23 AM",
 "relevancy": 1.0,
 "relevant": false,
 "text": "********************\nShadow Guardian 1.0.1 Apk\nhttp://urlin.us/cusxw\n(Copy & Paste link)\n********************\n\n\n\n\n\n\n\n\n\n\n\n\n\n\n\n\n\n\n\n\n\n\n\n\n\n\n\n\n\n\n\n\n\n\n\n\n\n\n\n\n\n\nShadow Guardian HD Apk Download+Data v1.0.6 Latest Version .\nShadow Guardian HD Mod Apk is an action game for Android Download Free From Androidpureapk Description Shadow Guardian HD is a very beautiful action game for Android .\nhttps://www.androidpureapk.com/2016/05/shadow-guardian-hd-apk...\n\nShadow Guardian HD apk download SD Data 1.0.1 free full .\nShadow Guardian HD apk download SD Data 1.0.1 free full Android cracked , Download APK Full, Shadow Guardian HD apk download SD Data 1.0.1 free full Android cracked\nhttps://downloadyourapk.blogspot.com/2013/05/shadow-guardian-hd...\n\nShadow Guardian 1.0.1.apk download - 2shared\nShadow Guardian 1.0.1.apk download at 2shared.. file Shadow Guardian 1.0.1.apk download at www.2shared.com.\nhttps://www.2shared.com/file/iP354JX9/Shadow_Guardian_101.html\n\nDownload Shadow guardian 1 0 0 apk files from TraDownload\nHere you can download free shadow guardian 1.0.0 apk shared files found in our database: Shadow Guardian 1.0.1.apk from 4shared.com host Shadow Guardian v1.0.1.apk .\nhttps://tradownload.info/results/shadow-guardian-1-0-0-apk.html\n\nShadow guardian HD v1.0.6 APK+Data Free Download [!Full .\nShadow guardian HD v1.0.6 APK Free Download+ 0bb data latest version.. Download Full APK of Shadow guardian HD v1.0.6 free for android.\nhttps://androidgamesspot.com/shadow-guardian-hd-apk-data\n\nDownload Shadow guardian files from TraDownload\nHere you can download free shadow guardian shared files found in our database: Shadow Guardian.apk from mediafire.com host shadow guardian 1 0 0 ipa LetItBit Shadow .\nhttps://tradownload.net/results/shadow-guardian.html\n\nshadow guardian apk\nHola Chicos En Este Video Les Presento El juego shadow guardian POR ESTOS MOMENTOS VOY A\nhttps://www.youtube.com/watch?v=lWkjc0O670k\n\nShadow Guardian Apk HD v1.0.0 With Data - Mad Loader\nIn Shadow Guardian Apk you will embark on an epic quest with an intriguing scenario, explore the world and escape the enemy armies that are hot on your heels.. Reach .\nhttps://madloader.com/shadow-guardian-apk\n\nDownload Shadow guardian 1 0 0 apk files - TraDownload\nHere you can download shadow guardian 1.0.0 apk shared files: Shadow Guardian 1.0.1.apk 4shared.com Shadow Guardian v1.0.1.apk 4shared.com 2.69 MB Shadow Guardian HD .\nhttps://tradownload.biz/results/shadow-guardian-1-0-0-apk.html\n\nShadow Guardian HD v1.0.6 APK Free Download (Latest) for .\nDownload Shadow Guardian HD (Offline) v1.0.6 game APK+data+obb files latest version for Android smartphones and tablets for free.\nhttps://www.androidsmobileapps.com/shadow-guardian-hd.  5f91d47415",
 "title": "Shadow Guardian 101 Apk"
}