{
 "espireDate": "N",
 "format": "text",
 "jSonReasons": [
  "lg_en",
  "re_url"
 ],
 "key": "NpYLP5xt",
 "pasteDate": "Feb 26, 2018, 12:18:28 AM",
 "relevancy": 2.0,
 "relevant": false,
 "text": "********************\nHorse Sex 2050 3gp.11\nhttp://urlin.us/dafrc\n(Copy & Paste link)\n********************\n\n\n\n\n\n\n\n\n\n\n\n\n\n\n\n\n\n\n\n\n\n\n\n\n\n\n\n\n\n\n\n\n\nAnimal Sex Tube - free animal porn, dog sex, horse fuck .\nanimal sex videos horse sex dog porn with human beastiality porn videos bestiality zoo tube woman with dog animal porn horse cum on girl\n\nanimal sex xxx Videos - Free Porn Videos - Heavy-R.com\nWatch free animal sex xxx videos at Heavy-R, a completely free porn tube offering the world's most hardcore porn videos.\n\nFree 2050 horse sex video com Download womensex co n XXX .\n2050 horse sex video com mobile xxx.. Uploaded: 17/01/26 Asa akira eres lo mejor te amo big eran.xxx.com download co rompimage rompimage .\n\nHorse Xxx Porn Videos  Pornhub.com\nWatch Horse Xxx porn videos for free, here on Pornhub.com.. Sort movies by Most Relevant and catch the best Horse Xxx .. and the number 1 free sex community on .\n\nsex 2050 for horse and girl sex video - Animal Porn - Zoofilia\nWild animal porn with real animals! Tons of nasty videos for you on-line without downloads.\n\nBadwap Sex2050 Indian Sex videos Sex2050.Com sex 2050 sex .\nBadwap free hd mobile sex porn site with sex2050 gives you best sex videos sex stories contents badwap.com sex2050.com\n\nThe horse cocks plant neighborhood Full 1080p 60fps .\nHD cocks full horse.. Related videos.. 62 16:13.. Moms Teach Sex  Sexy mom swaps cum with daughter 138 12:21.. 100%.\n\nAnimal Sex Porn - dog sex, horse sex, zoo sex, beastiality .\nIf you like animal fucking and animal porn videos and movies visit www.animalsexporn.net with tube galleries of animal sex lovers\n\nwww.sex2050 com, www.sex2050 com movie\npedofil porn sex Porno hairy online xxx films horse sex incestiporno A,AXXXX sexdikketits long porn films brazilian prostate por spy porno porn 13 years old zoofilia .\n\nAnimal sex videos\nDude prefers the mare's cunt Group Sex, Horse, Outdoor 00:03:34 Guy shoves the dong in mare's cunt while two g 37882.  006b59bca7",
 "title": "Horse Sex 2050 3gp11"
}