{
 "espireDate": "N",
 "format": "text",
 "jSonReasons": [
  "lg_tr",
  "kw_bot",
  "re_url"
 ],
 "key": "UarvGGkz",
 "pasteDate": "Feb 28, 2018, 7:08:27 AM",
 "relevancy": 1.0,
 "relevant": false,
 "text": "shama 24\n\n\n\n   ,   \n\n \n\n\nhttp://shamarc.shop\nhttp://shama-shop.pw\nhttp://dmsbita.biz\nhttp://bioticrc.com\nhttp://24ddd.org\nhttp://royalrc.co\nhttp://chaplin24.co\nhttp://domsbita.co\nhttp://molot.co\nhttp://kommersant.pw\nhttp://chem-24.pw\nhttp://sugar-shops.bz\nhttp://vitalya-bro.bz\nhttp://speedliner24.co\nhttp://aushka.com\n\n\n\n  \n  \n  \n\nhttp://obhod.biz\nhttp://toronline.biz\nhttp://snowden.pw\nhttp://vobhod.biz\nhttp://obhod.info\n\n\n\n\n\n\n\n\n\n\n\n\n\n\nshama\nshama shop\nshama biz\nshama shop biz\nshama \nshama shop \nshama rc\nshama   \nshama biz  \nshama shop   \nshama rc biz\nshama shop  \nshama biz   \nshama shop biz  \nshama ws\nshama shop biz   \nhttp shama\nshama cc\nhttp shama shop\nshama wc\nshama 24\nshama 5\nshama shop telegram\nshama hop\nshama shop ws\nshama shop 24\nshama shop 24 biz\nshama \nwww shama\nshama shop   \nshama rc cc\nshama shop \nshama shop biz    \nshama shop rc\nshama 5 biz\nshama ru\nshama shop24\nshama com\nshama shom5biz\nshama shop24 biz\nshama sikander\nshama shop wc\nshama ashna\nshama sham\nshama shop w s\nshama shop rc biz\nshama tayson\nshama keladi choydan\nshama shop  \ngavriel liraz shama\nshamarc biz\nshamarc \nklad ms\nshamarc ws\nshamarc biz \nklad biz\n24 biz\n \nklad ms biz\nms biz\n  \n   \n  24\n  \n  24 \n  \n  24   \n  24    \n    \n  \n  \n  ws\n    \n  buz5 bus\n  \n  \n   \n   \n  \n \n     \n  \n \n   \n  \n    \n  \n  biz\n  \n  26\n  24 biz\nrutmix\nrutmix cc\nrutmix cc     \nhttps rutmix cc\nrutmix cch\nhttp rutmix cc\nrutmix support \ndom sbita\ndom sbita biz\ndom sbita net\ndom sbita  \ndom sbita 24\ndom sbita com\ndom sbita 24 biz\ndom sbita   \ndom sbita biz  \ndom sbita com  \ndom sbita vip\ndom sbita net  \ndom sbita biz   \n24dd\n24dd biz\n24dd \n24dd biz  \n24dd  \n24dd biz   \nhttp 24dd\nhttps 24dd\nhttps 24dd biz\nhttp 24dd biz\n24dd  \n24dd biz \ndaffy 24dd\ndaffy 24dd biz\n24dd biz  \n24dd zazor\n24dd biz    \n24dd biz \n24dd biz   \ndaffy drugs 24dd biz\nzazor 24dd biz\n24dd biz \n24dd ru\n 24dd\n24dd vip\n24dd biz omsk\nwww 24dd\n24dd biz \nhttp 24dd biz \nwww 24dd biz\n24dd biz   zazor\n24dd biz \n24dd \n24dd biz bot\n24dd biz ml\n24dd bot\n24dd diz\n24dd vip city id 25\nhttp 24dd biz   \n24dd biz    \nhttp 24dd biz \nhttp 24dd biz ml rus\n24dd biz karamelka\nhttp 24dd biz check\n24dd biz    zazor\n24dd biz     \n24dd biz \nhttp 24dd biz    \n24dd biz \n24dd biz   \ndaffy drugs\ndaffy drugs biz\ndaffy drugs 24\ndaffy drugs 24 biz\ndaffy drugs  \ndaffy drugs \ndaffy drugs biz  \ndaffy drugs com\ndaffy drugs   \ndaffy drugs 24 biz   \ndaffy drugs legalrc\ndaffy drugs irkutsk legalrc com\ndaffy drugs 24 cc\ndaffy drugs telegram\ndaffy drugs org\nhttp daffy drugs org\ndaffy drugs 24 7\nramp\n \n  \n  \nhydra  \n  \nhydra   \n   \n   \n   \n    \n  \n  ramp\n  \n  \nhydra   \n  \n  \n   \n  \nramp   \n   \n  \n  \nruklad    \n    \n  telegram\n  \nhydra   \n    \n    \n      \nhydra   \nbioticrc\nbioticrc biz\n bioticrc\nbioticrc biz  \nbioticrc 24\nbioticrc 24 biz\nbioticrc biz   \nbioticrc   \nhttp bioticrc biz\nbioticrc biz  \nbioticrc biz    \nbioticrc biz  \nbioticrc 24 biz   \nbioticrc biz zazor\nbioticrc biz     \nbioticrc biz    zazor\nwww bioticrc biz\nbioticrc biz cf\nramp \nspeedliner\nspeedliner 24\nspeedliner biz\nspeedliner 24 biz\nspeedliner 24 biz  \nspeedliner omsk\nspeedliner 24 biz omsk\nspeedliner 24 biz   \n   speedliner 24\nspeedliner 24 biz   \nspeedliner 24 biz \n fill speedliner\nspeedliner \n arlen ness speedliner\nroyalrc\nroyalrc biz\nroyalrc \nroyalrc biz  \nroyalrc  \nroyalrc biz   \n      royalrc\nroyalrc biz    \nroyalrc biz   \n   royalrc biz\n  qiwi  royalrc biz\nchaplin24 biz\nchaplin24 biz  \nchaplin24 biz   \nchaplin24 biz omsk\nhttp chaplin24 biz\nchaplin24 biz   \nchaplin24 biz   \nhttps chaplin24 biz\nchaplin24 biz zazor\nchaplin24 biz \nchaplin24 biz    \n \n  24\n  \n  24 \n   \n  \n  \n  24 \n   \n    \n    \n    \n  24 biz\n    \n     zazor \n  24  \naushka\naushka biz\naushka biz  \naushka biz   \nwww aushka\naushka ru\nermak aushka\nermak aushka ru\nwww ermak aushka ru\nwww aushka ru\naushka biz    \naushka biz \nwww aushka biz\naushka biz    \nhttp aushka biz\nhttps aushka biz",
 "title": "shama 24\n"
}