{
 "espireDate": "N",
 "format": "text",
 "jSonReasons": [
  "re_url",
  "lg_en"
 ],
 "key": "wMx2GQNf",
 "pasteDate": "Feb 17, 2018, 11:42:27 PM",
 "relevancy": 1.0,
 "relevant": false,
 "text": "********************\n[FULL] Vajva Re Vajva Marathi 41\nhttp://urlin.us/d0ne9\n(Copy & Paste link)\n********************\n\n\n\n\n\n\n\n\n\n\n\n\n\n\n\n\n\n\n\n\n\n\n\n\n\n\n\n\n\n\n\n\n\n\n\n\n\n\n\n\n\n\n\nVajva Re Vajva Dholtasha Vajva Free Download VipMarathi.com\nVajva Re Vajva Dholtasha Vajva marathi movie songs download,Vajva Re Vajva Dholtasha Vajva Marathi Movie mp3 Free, Vajva Re Vajva Dholtasha Vajva full .. 7.41 mb .\n\nFree download marathi movie vajva re vajava websites .\nLook at most relevant Free download marathi movie vajva re vajava websites out of 21.4 Thousand at KeyOptimize.com.. Free download marathi movie vajva re vajava found .\n\nVajva Re Vajva Dholtasha Vajva - Letest Marathi Movie .\nVajva Re Vajva Dholtasha Vajva marathi, songs download mp3,Marathi,Songs,Marathi,Vajva Re Vajva Dholtasha Vajva Movie, Mp3 Ringtone,dJ mix songs,marathi dj remix .\n\nWajva Re Wajva (1993) - IMDb\nFULL CAST AND CREW  TRIVIA .. Best Marathi Movies - MUST WATCH .. Title: Wajva Re Wajva (1993) 7.6 /10.. Want to share IMDb's .\n\nhi yuga yuganchi nati ( -     ,  .\nMarathi Movie - Vajva Re Vajva.. Marathi Movie - Vajva Re Vajva.. Skip navigation Sign in.. Search.. .\n\nVajva Re Vajva Dholtasha Vajva Free Download FunMarathi.in\nVajva Re Vajva Dholtasha Vajva Marathi Movie Mp3 Songs Download, , full video songs download, HD MP4, dvdrip, lyrics, ringtones, Trailer, Movie watch online.\n\nWajva Re Wajva (1992) - Cinestaan.com\nWajva Re Wajva Marathi movie: Cast and Crew, release date, news, posters, trailers and songs - Cinestaan.com\n\nHi Yuga Yuganchi Nati - YouTube\nA very soft, melodious and romantic Marathi song.sung by Suresh Wadkar and Anuradha Paudwal.From Vajwa Re Vajwa\n\nFirearms and Hunting\nVajwa Re Vajwa (1992) - Marathi Movie Watch Online.. Starring - Prashant Damle, Ashok Saraf, Nishigandha Vad, Ajikya Dev, Kishori Shahane Director - Not Available .\n\nMarathi Movies & TV Shows VCD & DVD Online - Amazon.in\nOnline shopping for Marathi from a great selection at Movies & TV Shows Store.. .. Marathi Movies & TV Shows.. .  bb84b2e1ba",
 "title": "FULL Vajva Re Vajva Marathi 41"
}