{
 "espireDate": "N",
 "format": "text",
 "jSonReasons": [
  "lg_vi",
  "re_email"
 ],
 "key": "LnDBpStj",
 "pasteDate": "Feb 21, 2018, 8:21:06 AM",
 "relevancy": 2.0,
 "relevant": true,
 "text": "ustream@mail.com\nbaywolf@ymail.com\ncashmycheck@mail.com\nfog@cyberdude.com \nlaw@angelic.com \nfaith@atheist.com \nShit@angelic.com \nRay@innocent.com \nConspiracy@politician.com \npan@activist.com \nGag@reborn.com\nThe@protestant.com\nJaw@oath.com\nEpic@lawyer.com\ngenius@atheist.com\nsnipe@activist.com\nfetus@reborn.com\nretired@accountant.com\nstatutory@priest.com\nteacup@london.com",
 "title": ""
}