{
 "espireDate": "N",
 "format": "text",
 "jSonReasons": [
  "kw_crack",
  "re_url",
  "lg_en"
 ],
 "key": "tkPzXXJ1",
 "pasteDate": "Feb 8, 2018, 6:06:05 AM",
 "relevancy": 1.0,
 "relevant": true,
 "text": "********************\nDownload Fieldrunners 2 Pc Full Crack\nhttp://urlin.us/cqqpe\n(Copy & Paste link)\n********************\n\n\n\n\n\n\n\n\n\n\n\n\n\n\n\n\n\n\n\n\n\n\n\n\n\n\n\n\n\n\n\n\n\n\n\n\n\n\n\n\n\n\n\n\nFieldrunners,,,2,,,Full,,,PC,,,Game,,,Overview.,,,Fieldrunners,,,2,,,Download,,,Free,,,Full,,,Game,,,is,,,a,,,tower,,,defense,,,video,,,game,,,,the,,,sequel,,,to,,,Fieldrunners,,,,developed,,,by,,,Subatomic,,,Studios.. FIELDRUNNERS,,2,,PC,,GAME,,FREE,,DOWNLOAD.,,Fieldrunners,,2,,is,,an,,Action,,,Casual,,and,,Strategy,,game,,for,,PC,,published,,by,,Subatomic,,Studios,,LLC,,in,,2013.,,Defend,,against,,the,,.. Field,Runner,2,Free,Download,For,Pc,.,2,for,pc,crack,fieldrunners,2,for,pc,download,fieldrunners,2,for,pc,free,download,fieldrunners,2,for,pc,free,download,full,.. Download,,Game,,Fieldrunners,,2,,PC,,Full,,Version,,-,,May,,,Game,,strategy,,is,,one,,of,,your,,favorite,,games.,,And,,it's,,been,,a,,lot,,of,,strategy,,PC,,game,,genre.. Fieldrunners,,2,,is,,a,,tower,,defense,,.,,where,,gamers,,directly,,download,,full,,version,,free,,pc,,game,,.,,You,,will,,need,,to,,copy,,the,,crack,,to,,your,,install,,directory,,ex,,.. Fieldrunners,,,2,,,is,,,an,,,Action,,,,.,,,Fieldrunners,,,2,,,Free,,,PC,,,Download.,,,by,,,Ali>,,,in,,,Action,Casual,Strategy,,,-,,,5,,,November,,,2015,,,.,,,Fieldrunners,,,2,,,is,,,an,,,Action,,,,.. Fieldrunners,,2,,v1.1,,Apk,,Full,,for,,Android,,-,,Free,,Download,,Fieldrunners,,2,,v1.1,,Apk,,Full,,for,,Android,,Apk,,Ipa,,Full,,App,,Game,,Android,,iPhone,,Java,,Nokia,,PC,,Mod,,Jar,,Pro,,Full,,.. Get,ready,to,DEFEND,THE,WORLD!,The,biggest,sequel,in,tower,defense,history,is,finally,here:,Fieldrunners,2,has,arrived!,From,Subatomic,Studios,,creators,of,the,award,.. Tabtight,,,professional,,,,free,,,when,,,you,,,need,,,it,,,,VPN,,,service,,,Download,,,fieldrunners,,,2,,,pc,,,full,,,crack.. PC,,,,,,Iso,,,,,,Cracked,,,,,,Torrent,,,,,,Download,,,,,,Free,,,,,,Full,,,Game,,,Get,,,ready,,,to,,,DEFEND,,,THE,,,WORLD!,,,The,,,biggest,,,sequel,,,in,,,tower,,,[.],,,.,,,Fieldrunners,,,2,,,REPACK-TINYISO.. Trong,khi,Fieldrunners,2,,qun,lnh,s,khng,di,chuyn,theo,mt,con,ng,c,nh,,m,thay,i,l,trnh,try,thuc,vo,cch,sp,xp,.. Fieldrunners,,,2,,,REPACK,,,,free,,,download,,,game,,,,full,,,version,,,,pc,,,games,,,,download,,,game. Compatible,with,Mini-ITX,,MicroATX,,E-ATX,and,XL-ATX,motherboards,Tool-free,drive,installation,,with,3,x,5.25-inch,external,,6,x,combo,3.5-inch/2.5-inch,internal,and,4,x,2.5-inch,internal. Compatible,,,with,,,Mini-ITX,,,,MicroATX,,,,EATX,,,(12in,,,x,,,10.6in),,,motherboards,,,Tool,,,free,,,drive,,,installation,,,,2,,,x,,,5.25,,,inch,,,external,,,,2,,,x,,,3.5,,,inch,,,external,,,and,,,3,,,x,,,2.5,,,inch,,,drive,,,bays,,,2,,,x,,,USB,,,3.0. Download,Fieldrunners,for,free.,Fieldrunners,-,In,this,game,your,goal,is,to,defend,and,control,the,field,using,a,diverse,selection,of,upgradeable,towers.. Fieldrunners,,2,,apk,,mod,,fulL,,klik,,pada,,Download,,Cepat,,untuk,,secara,,otomatis,,men-download,,dan,,menyalin,,data.. Fieldrunners,2,is,the,sequel,to,the,megapopular,Fieldrunners,,which,has,occupied,a,spot,high,on,the,iOS,App,Store,charts,for,months.. FieldRunners,2,full,version,PC,game,free,download,,.,The,games,is,crack,FieldRunners,2,download,with,torrent,network,and,mirror,single,Rar,,Zip,,ISO,,.. Look,Up,Quick,Results,Now!,Find,Related,Search,and,Trending,Suggestions,Here.. Fieldrunners,,2,,Free,,Download,,for,,PC,,is,,a,,tower,,defense,,video,,game,,,the,,sequel,,to,,Fieldrunners,,,developed,,by,,Subatomic,,Studios.. FULL,GAME,,REPACK,,CRACKED,,TORRENT,Get,ready,to,DEFEND,THE,WORLD!,The,biggest,sequel,in,tower,defense,history,is,finally,here:,Fieldrunners,2,has,arrived!. Compatible,,,with,,,Mini-ITX,,,,MicroATX,,,and,,,EATX,,,(12in,,,x,,,10.6in),,,motherboards,,,Tool,,,free,,,drive,,,installation,,,,2,,,x,,,3.5,,,inch,,,internal,,,and,,,3,,,x,,,2.5,,,inch,,,drive,,,bays,,,2,,,x,,,USB,,,3.0,,,ports,,,,2,,,x,,,USB,,,2.0,,,ports,. Fieldrunners,,2,,Crack.,,Fieldrunners,,2,,Crack.,,Pinterest.,,Explore,,Pc,,Games,,,Video,,Games,,,and,,more!,,Products;,,.,,Full,,pc,,software,,free,,download,,Archives,,-,,Dieorhack,,.. Download,fieldrunners,2,pc,full,crack,,,.,Download,game,fieldrunners,2,v1.3,full,crack,min,ph,,Ti,fieldrunners,2,android,phin,bn,chun.. Fieldrunners,,2,,PC,,Full,,Version,,Game,,Free,,Download.,,Screenshots.,,System,,Requirements,,of,,Fieldrunners,,2,,Free,,Download.,,.,,Open,,\"Crack\",,folder,,,.. Fieldrunners,,,2,,,Repack,,,-,,,(TiNYiSO),,,,,,FULL,,,PC,,,Game.torrent,,,download,,,.,,,Crack:Yes.,,,Download,,,Type:,,,.,,,FULL,,,PC,,,Game.torrent,,,download.,,,Gas,,,Guzzlers,,,Extreme,,,.. Compatible,with,Mini-ITX,,MicroATX,,ATX,,E-ATX,and,XL-ATX,motherboards,Tool-free,drive,installation,with,3,x,5.25-inch,external,,6,x,combo,3.5-inch/2.5-inch,internal,and,4,x,2.5-inch. Download,,,ti,,,Field,,,Runners,,,1,,,,2,,,full,,,cho,,,Pc,,,,laptop,,,,my,,,tnh.,,,.,,,Download,,,Aoe,,,3,,,Full,,,Crack,,,05/04/2013;,,,Download,,,Game,,,Rise,,,of,,,Nation,,,full,,,v,,,m,,,rng,,,.. Fieldrunners,l,mt,game,.,Pass,gii,nn,mc,nh,l,full,crack,hoc,fullcrackpc.,Premium,Filehost,Link,Generator,,Free,Hng,dn,download,game,.. Look,Up,Quick,Results,Now!,Find,Related,Search,and,Trending,Suggestions,Here.  520aad1ef5",
 "title": "Download Fieldrunners 2 Pc Full Crack"
}